aprs_tocall/__init__.py
aprs_tocall/__main__.py
aprs_tocall/test.py
aprs_tocall/tocalls.yaml
aprs_tocall-0.1.3.dist-info/entry_points.txt
aprs_tocall-0.1.3.dist-info/WHEEL
aprs_tocall-0.1.3.dist-info/METADATA
aprs_tocall-0.1.3.dist-info/RECORD
