Metadata-Version: 2.1
Name: aprs-tocall
Version: 0.1.3
Summary: Parses APRS "tocalls" or tocalls.txt / tocalls.yaml easily in Python
Home-page: https://github.com/xssfox/aprs_tocall
License: WTFPL
Author: xss
Author-email: michaela@michaela.lgbt
Requires-Python: >=3.10,<4.0
Classifier: License :: Other/Proprietary License
Classifier: Programming Language :: Python :: 3
Classifier: Programming Language :: Python :: 3.10
Requires-Dist: PyYAML (>=6.0.1,<7.0.0)
Project-URL: Repository, https://github.com/xssfox/aprs_tocall
